supaclaude/__init__.py
supaclaude/cli.py
supaclaude-0.1.0.dist-info/METADATA
supaclaude-0.1.0.dist-info/WHEEL
supaclaude-0.1.0.dist-info/entry_points.txt
supaclaude-0.1.0.dist-info/licenses/LICENSE
supaclaude-0.1.0.dist-info/RECORD
