Metadata-Version: 2.4
Name: supaclaude
Version: 0.1.0
Summary: Enhanced CLI wrapper for Claude with beautiful JSON formatting
Project-URL: Homepage, https://github.com/yourusername/supaclaude
Project-URL: Repository, https://github.com/yourusername/supaclaude
Project-URL: Issues, https://github.com/yourusername/supaclaude/issues
Author-email: Bryan Liu <your.email@example.com>
License-Expression: MIT
License-File: LICENSE
Keywords: ai,anthropic,claude,cli,formatting
Classifier: Development Status :: 4 - Beta
Classifier: Intended Audience :: Developers
Classifier: License :: OSI Approved :: MIT License
Classifier: Programming Language :: Python :: 3
Classifier: Programming Language :: Python :: 3.8
Classifier: Programming Language :: Python :: 3.9
Classifier: Programming Language :: Python :: 3.10
Classifier: Programming Language :: Python :: 3.11
Classifier: Programming Language :: Python :: 3.12
Classifier: Topic :: Software Development :: Libraries :: Python Modules
Classifier: Topic :: Terminals
Requires-Python: >=3.8
Requires-Dist: rich>=13.0.0
